ca_certificates/__init__.py
statsapi-0.0.0.dist-info/METADATA
statsapi-0.0.0.dist-info/WHEEL
statsapi-0.0.0.dist-info/top_level.txt
statsapi-0.0.0.dist-info/RECORD
