Metadata-Version: 2.4
Name: statsapi
Version: 0.0.0
Summary: Dummy statsapi package for PyPI
Author-email: Your Name <you@example.com>
Requires-Python: >=3.7
